README.md
setup.py
dueros/Base.py
dueros/Bot.py
dueros/Certificate.py
dueros/Constants.py
dueros/Intercept.py
dueros/Log.py
dueros/Nlu.py
dueros/Request.py
dueros/Response.py
dueros/Session.py
dueros/Utils.py
dueros/__init__.py
dueros/card/BaseCard.py
dueros/card/ImageCard.py
dueros/card/LinkAccountCard.py
dueros/card/ListCard.py
dueros/card/ListCardItem.py
dueros/card/StandardCard.py
dueros/card/TextCard.py
dueros/card/__init__.py
dueros/directive/BaseDirective.py
dueros/directive/__init__.py
dueros/directive/AppLauncher/LaunchApp.py
dueros/directive/AppLauncher/__init__.py
dueros/directive/AudioPlayer/AudioItemTypeEnum.py
dueros/directive/AudioPlayer/AudioPlayerInfo.py
dueros/directive/AudioPlayer/AudioPlayerInfoContent.py
dueros/directive/AudioPlayer/Play.py
dueros/directive/AudioPlayer/PlayBehaviorEnum.py
dueros/directive/AudioPlayer/PlayerInfo.py
dueros/directive/AudioPlayer/Stop.py
dueros/directive/AudioPlayer/StreamFormatEnum.py
dueros/directive/AudioPlayer/__init__.py
dueros/directive/AudioPlayer/Control/BaseButton.py
dueros/directive/AudioPlayer/Control/Button.py
dueros/directive/AudioPlayer/Control/FavoriteButton.py
dueros/directive/AudioPlayer/Control/LyricButton.py
dueros/directive/AudioPlayer/Control/NextButton.py
dueros/directive/AudioPlayer/Control/PlayPauseButton.py
dueros/directive/AudioPlayer/Control/PreviousButton.py
dueros/directive/AudioPlayer/Control/RadioButton.py
dueros/directive/AudioPlayer/Control/RecommendButton.py
dueros/directive/AudioPlayer/Control/RefreshButton.py
dueros/directive/AudioPlayer/Control/RepeatButton.py
dueros/directive/AudioPlayer/Control/RepeatButtonEnum.py
dueros/directive/AudioPlayer/Control/ShowFavoriteListButton.py
dueros/directive/AudioPlayer/Control/ShowPlayListButton.py
dueros/directive/AudioPlayer/Control/ThumbsUpDownButton.py
dueros/directive/AudioPlayer/Control/ThumbsUpDownButtonEnum.py
dueros/directive/AudioPlayer/Control/__init__.py
dueros/directive/Base/BasePlayerInfoContent.py
dueros_bot_master_alpha.egg-info/PKG-INFO
dueros_bot_master_alpha.egg-info/SOURCES.txt
dueros_bot_master_alpha.egg-info/dependency_links.txt
dueros_bot_master_alpha.egg-info/requires.txt
dueros_bot_master_alpha.egg-info/top_level.txt
