Metadata-Version: 1.0
Name: dueros-bot-master-alpha
Version: 2.1.3
Summary: Third party DuerOS Bot Python SDK
Home-page: https://github.com/jokenwang/bot-sdk-python
Author: jack
Author-email: mupdf@sina.com
License: UNKNOWN
Keywords: DuerOS Bot
Platform: UNKNOWN
